tensor_util_collection/__init__.py
tensor_util_collection/decorators.py
tensor_util_collection/geometry.py
tensor_util_collection-0.0.2.dist-info/LICENSE
tensor_util_collection-0.0.2.dist-info/METADATA
tensor_util_collection-0.0.2.dist-info/WHEEL
tensor_util_collection-0.0.2.dist-info/top_level.txt
tensor_util_collection-0.0.2.dist-info/RECORD
